Fpga/ip_repo/axi2pid_1.0/src/pid_value.v
`timescale 1ns / 1ps


module PID_value#(
           parameter VAL_LENGTH = 32
       )(
           input wire sys_clk,
           input wire sys_rst_n,

           input wire signed [VAL_LENGTH - 1: 0] err_val,
           input wire signed [VAL_LENGTH - 1: 0] int_val,
           input wire signed [VAL_LENGTH - 1: 0] dif_val,
           input wire signed [VAL_LENGTH - 1: 0] kp,
           input wire signed [VAL_LENGTH - 1: 0] ki,
           input wire signed [VAL_LENGTH - 1: 0] kd,
           input wire signed [VAL_LENGTH - 1: 0] uk_max,
           input wire signed [VAL_LENGTH - 1: 0] uk_min,

           output wire signed [VAL_LENGTH - 1: 0] uk
       );
reg signed [VAL_LENGTH - 1: 0] uk_w;

always @(posedge sys_clk or negedge sys_rst_n) begin
    if (!sys_rst_n) begin
        uk_w <= {VAL_LENGTH{1'd0}};
    end
    else begin
        uk_w <= err_val * kp + int_val * ki + dif_val * kd;
    end
end

assign uk = (uk_w > uk_max) ? (uk_max) : ((uk_w < uk_min) ? uk_min : uk_w);

endmodule

Fpga/ip_repo/axi2pid_1.0/src/pid_inc_value.v
`timescale 1ns / 1ps


module PID_incr_value #(
           parameter VAL_LENGTH = 32
       )(
           input wire sys_clk,
           input wire sys_rst_n,

           input wire signed [VAL_LENGTH - 1: 0] ek0,
           input wire signed [VAL_LENGTH - 1: 0] ek1,
           input wire signed [VAL_LENGTH - 1: 0] int_max,
           input wire signed [VAL_LENGTH - 1: 0] int_min,
           input wire signed [VAL_LENGTH - 1: 0] dif_max,
           input wire signed [VAL_LENGTH - 1: 0] dif_min,

           output wire signed [VAL_LENGTH - 1: 0] int_val_f,
           output wire signed [VAL_LENGTH - 1: 0] dif_val_f
       );
reg signed [VAL_LENGTH - 1: 0] int_val;
wire signed [VAL_LENGTH - 1: 0] dif_val;

//calculate integratal value
always @(posedge sys_clk or negedge sys_rst_n) begin
    if (!sys_rst_n) begin
        int_val <= {VAL_LENGTH{1'd0}};
    end
    else begin
        int_val <= int_val + ek0;
    end
end

assign int_val_f = (int_val > int_max) ? (int_max) : ((int_val < int_min) ? int_min : int_val);

//calculate differential value
assign dif_val = ek0 - ek1;
assign dif_val_f = (dif_val > dif_max) ? (dif_max) : ((dif_val < dif_min) ? dif_min : dif_val);

endmodule

Fpga/ip_repo/axi2pid_1.0/src/pid_error.v
`timescale 1ns / 1ps


module PID_error #(
           parameter VAL_LENGTH = 32
       )(
           input wire sys_clk,
           input wire sys_rst_n,

           input wire signed [VAL_LENGTH - 1: 0] target,
           input wire signed [VAL_LENGTH - 1: 0] current_value,
           output wire signed [VAL_LENGTH - 1: 0] ek0,
           output reg signed [VAL_LENGTH - 1: 0] ek1
       );

assign ek0 = target - current_value; //calculate error

always @(posedge sys_clk or negedge sys_rst_n) begin
    if (!sys_rst_n) begin
        ek1 <= {VAL_LENGTH{1'd0}};
    end
    else begin
        ek1 <= ek0;
    end
end
endmodule

Fpga/ip_repo/axi2pid_1.0/src/pid_top.v
`timescale 1ns / 1ps 
// `define USING_INNER_PWM
`include "pid_error.v"
`include "pid_inc_value.v"
`include "pid_value.v"

module pid_top #(
           parameter CLK_VAL_MHZ = 50,
           parameter VAL_LENGTH = 32
       )(
           input sys_clk,
           input sys_rst_n,

           input wire signed [VAL_LENGTH - 1: 0] target,
           input wire signed [VAL_LENGTH - 1: 0] current_value,
           input wire signed [VAL_LENGTH - 1: 0] int_max,
           input wire signed [VAL_LENGTH - 1: 0] int_min,
           input wire signed [VAL_LENGTH - 1: 0] dif_max,
           input wire signed [VAL_LENGTH - 1: 0] dif_min,
           input wire signed [VAL_LENGTH - 1: 0] uk_max,
           input wire signed [VAL_LENGTH - 1: 0] uk_min,
           input wire signed [VAL_LENGTH - 1: 0] kp,
           input wire signed [VAL_LENGTH - 1: 0] ki,
           input wire signed [VAL_LENGTH - 1: 0] kd,
           output wire signed [VAL_LENGTH - 1: 0] pid_out
       );
wire signed [VAL_LENGTH - 1: 0] ek0;
wire signed [VAL_LENGTH - 1: 0] ek1;
wire signed [VAL_LENGTH - 1: 0] ek2;
wire signed [VAL_LENGTH - 1: 0] int_value;
wire signed [VAL_LENGTH - 1: 0] dif_value;

PID_error #(
              .VAL_LENGTH ( VAL_LENGTH ))
          u_PID_error(
              //ports
              .sys_clk ( sys_clk ),
              .sys_rst_n ( sys_rst_n ),
              .target ( target ),
              .current_value ( current_value ),
              .ek0 ( ek0 ),
              .ek1 ( ek1 )
          );

PID_incr_value #(
                   .VAL_LENGTH ( VAL_LENGTH ))
               u_PID_incr_value(
                   //ports
                   .sys_clk ( sys_clk ),
                   .sys_rst_n ( sys_rst_n ),
                   .ek0 ( ek0 ),
                   .ek1 ( ek1 ),
                   .int_max ( int_max ),
                   .int_min ( int_min ),
                   .dif_max ( dif_max ),
                   .dif_min ( dif_min ),
                   .int_val_f ( int_value ),
                   .dif_val_f ( dif_value )
               );

PID_value #(
              .VAL_LENGTH ( VAL_LENGTH ))
          u_PID_value(
              //ports
              .sys_clk ( sys_clk ),
              .sys_rst_n ( sys_rst_n ),
              .err_val ( ek0 ),
              .int_val ( int_value ),
              .dif_val ( dif_value ),
              .uk_max(uk_max),
              .uk_min(uk_min),
              .kp ( kp ),
              .ki ( ki ),
              .kd ( kd ),
              .uk ( pid_out )
          );

// `ifdef USING_INNER_PWM
// pid_tim #(
//             .CLK_VAL_MHZ ( CLK_VAL_MHZ ))
//         u_pid_tim0(
//             //ports
//             .sys_clk ( sys_clk ),
//             .sys_rst_n ( sys_rst_n ),
//             .ctrl_value (  ),
//             .pwm ( pwm[0] )
//         );
// pid_tim #(
//             .CLK_VAL_MHZ ( CLK_VAL_MHZ ))
//         u_pid_tim1(
//             //ports
//             .sys_clk ( sys_clk ),
//             .sys_rst_n ( sys_rst_n ),
//             .ctrl_value (  ),
//             .pwm ( pwm[1] )
//         );
// pid_tim #(
//             .CLK_VAL_MHZ ( CLK_VAL_MHZ ))
//         u_pid_tim2(
//             //ports
//             .sys_clk ( sys_clk ),
//             .sys_rst_n ( sys_rst_n ),
//             .ctrl_value (  ),
//             .pwm ( pwm[2] )
//         );
// pid_tim #(
//             .CLK_VAL_MHZ ( CLK_VAL_MHZ ))
//         u_pid_tim3(
//             //ports
//             .sys_clk ( sys_clk ),
//             .sys_rst_n ( sys_rst_n ),
//             .ctrl_value (  ),
//             .pwm ( pwm[3] )
//         );
// `endif

endmodule

Fpga/ip_repo/axi2pid_1.0/src/pid_tb.v
`timescale 1ns / 1ps 
//////////////////////////////////////////////////////////////////////////////////
// Company:
// Engineer:
//
// Create Date: 2022/10/03 16:20:35
// Design Name:
// Module Name: pid_tb
// Project Name:
// Target Devices:
// Tool Versions:
// Description:
//
// Dependencies:
//
// Revision:
// Revision 0.01 - File Created
// Additional Comments:
//
//////////////////////////////////////////////////////////////////////////////////
`include "./pid_top.v"

module pid_tb();
// pid_top Parameters
parameter PERIOD = 10;
parameter CLK_VAL_MHZ = 50;
parameter VAL_LENGTH = 32;

// pid_top Inputs
reg sys_clk = 0;
reg sys_rst_n = 0;
reg signed [VAL_LENGTH - 1: 0] target = 0;
reg signed [VAL_LENGTH - 1: 0] current_value = 0;
reg signed [VAL_LENGTH - 1: 0] int_max = 0;
reg signed [VAL_LENGTH - 1: 0] int_min = 0;
reg signed [VAL_LENGTH - 1: 0] dif_max = 0;
reg signed [VAL_LENGTH - 1: 0] dif_min = 0;
reg signed [VAL_LENGTH - 1: 0] uk_max = 0;
reg signed [VAL_LENGTH - 1: 0] uk_min = 0;
reg signed [VAL_LENGTH - 1: 0] kp = 0;
reg signed [VAL_LENGTH - 1: 0] ki = 0;
reg signed [VAL_LENGTH - 1: 0] kd = 0;

// pid_top Outputs
wire signed [VAL_LENGTH - 1: 0] pid_out;


initial begin
    forever
        #(PERIOD / 2) sys_clk = ~sys_clk;
end


integer stage = 0;
always @(posedge sys_clk) begin
    case (stage)
        0: begin
            sys_rst_n = 1'b0;
            target = 1357;
            int_max = 50;
            int_min = -50;
            dif_max = 20;
            dif_min = -20;
            uk_max = 2500;
            uk_min = 500;
            kp = 1;
            ki = 3;
            kd = 2;
            stage = 1;
        end
        1: begin
            sys_rst_n = 1'b1;
            stage = 2;
        end
        2: begin
            current_value = pid_out / 10;
            stage = 2;
        end
        default: begin
            stage = 0;
        end
    endcase
end


pid_top #(
            .CLK_VAL_MHZ ( CLK_VAL_MHZ ),
            .VAL_LENGTH ( VAL_LENGTH ))
        u_pid_top_inst (
            .sys_clk ( sys_clk ),
            .sys_rst_n ( sys_rst_n ),
            .target ( target [VAL_LENGTH - 1: 0] ),
            .current_value ( current_value [VAL_LENGTH - 1: 0] ),
            .int_max ( int_max [VAL_LENGTH - 1: 0] ),
            .int_min ( int_min [VAL_LENGTH - 1: 0] ),
            .dif_max ( dif_max [VAL_LENGTH - 1: 0] ),
            .dif_min ( dif_min [VAL_LENGTH - 1: 0] ),
            .uk_max(uk_max),
            .uk_min(uk_min),
            .kp ( kp [VAL_LENGTH - 1: 0] ),
            .ki ( ki [VAL_LENGTH - 1: 0] ),
            .kd ( kd [VAL_LENGTH - 1: 0] ),

            .pid_out ( pid_out [VAL_LENGTH - 1: 0] )
        );

initial begin
    $dumpfile("pid_tb.vcd");
    $dumpvars();
    #1000;
    $finish();
    $stop();
end

endmodule

Fpga/ip_repo/axi2pid_1.0/src/pid_tb.vcd
$date
	Mon Oct 03 18:20:01 2022
$end
$version
	Icarus Verilog
$end
$timescale
	1ps
$end
$scope module pid_tb $end
$var wire 32 ! pid_out [31:0] $end
$var reg 32 " current_value [31:0] $end
$var reg 32 # dif_max [31:0] $end
$var reg 32 $ dif_min [31:0] $end
$var reg 32 % int_max [31:0] $end
$var reg 32 & int_min [31:0] $end
$var reg 32 ' kd [31:0] $end
$var reg 32 ( ki [31:0] $end
$var reg 32 ) kp [31:0] $end
$var reg 1 * sys_clk $end
$var reg 1 + sys_rst_n $end
$var reg 32 , target [31:0] $end
$var reg 32 - uk_max [31:0] $end
$var reg 32 . uk_min [31:0] $end
$var integer 32 / stage [31:0] $end
$scope module u_pid_top_inst $end
$var wire 32 0 current_value [31:0] $end
$var wire 32 1 dif_max [31:0] $end
$var wire 32 2 dif_min [31:0] $end
$var wire 32 3 int_max [31:0] $end
$var wire 32 4 int_min [31:0] $end
$var wire 32 5 kd [31:0] $end
$var wire 32 6 ki [31:0] $end
$var wire 32 7 kp [31:0] $end
$var wire 1 * sys_clk $end
$var wire 1 + sys_rst_n $end
$var wire 32 8 target [31:0] $end
$var wire 32 9 uk_max [31:0] $end
$var wire 32 : uk_min [31:0] $end
$var wire 32 ; pid_out [31:0] $end
$var wire 32 < int_value [31:0] $end
$var wire 32 = ek1 [31:0] $end
$var wire 32 > ek0 [31:0] $end
$var wire 32 ? dif_value [31:0] $end
$scope module u_PID_error $end
$var wire 32 @ current_value [31:0] $end
$var wire 1 * sys_clk $end
$var wire 1 + sys_rst_n $end
$var wire 32 A target [31:0] $end
$var wire 32 B ek0 [31:0] $end
$var reg 32 C ek1 [31:0] $end
$upscope $end
$scope module u_PID_incr_value $end
$var wire 32 D dif_max [31:0] $end
$var wire 32 E dif_min [31:0] $end
$var wire 32 F ek0 [31:0] $end
$var wire 32 G ek1 [31:0] $end
$var wire 32 H int_max [31:0] $end
$var wire 32 I int_min [31:0] $end
$var wire 1 * sys_clk $end
$var wire 1 + sys_rst_n $end
$var wire 32 J int_val_f [31:0] $end
$var wire 32 K dif_val_f [31:0] $end
$var wire 32 L dif_val [31:0] $end
$var reg 32 M int_val [31:0] $end
$upscope $end
$scope module u_PID_value $end
$var wire 32 N dif_val [31:0] $end
$var wire 32 O err_val [31:0] $end
$var wire 32 P int_val [31:0] $end
$var wire 32 Q kd [31:0] $end
$var wire 32 R ki [31:0] $end
$var wire 32 S kp [31:0] $end
$var wire 1 * sys_clk $end
$var wire 1 + sys_rst_n $end
$var wire 32 T uk_max [31:0] $end
$var wire 32 U uk_min [31:0] $end
$var wire 32 V uk [31:0] $end
$var reg 32 W uk_w [31:0] $end
$upscope $end
$upscope $end
$upscope $end
$enddefinitions $end
#0
$dumpvars
b0 W
b0 V
b0 U
b0 T
b0 S
b0 R
b0 Q
b0 P
b0 O
b0 N
b0 M
b0 L
b0 K
b0 J
b0 I
b0 H
b0 G
b0 F
b0 E
b0 D
b0 C
b0 B
b0 A
b0 @
b0 ?
b0 >
b0 =
b0 <
b0 ;
b0 :
b0 9
b0 8
b0 7
b0 6
b0 5
b0 4
b0 3
b0 2
b0 1
b0 0
b0 /
b0 .
b0 -
b0 ,
0+
0*
b0 )
b0 (
b0 '
b0 &
b0 %
b0 $
b0 #
b0 "
b0 !
$end
#5000
b1111010000100100000 !
b1111010000100100000 ;
b1111010000100100000 V
b100111000100000 ?
b100111000100000 K
b100111000100000 N
b1 /
b10 '
b10 5
b10 Q
b11 (
b11 6
b11 R
b1 )
b1 7
b1 S
b1111010000100100000 .
b1111010000100100000 :
b1111010000100100000 U
b1001100010010110100000 -
b1001100010010110100000 9
b1001100010010110100000 T
b11111111111111111011000111100000 $
b11111111111111111011000111100000 2
b11111111111111111011000111100000 E
b100111000100000 #
b100111000100000 1
b100111000100000 D
b11111111111111110011110010110000 &
b11111111111111110011110010110000 4
b11111111111111110011110010110000 I
b1100001101010000 %
b1100001101010000 3
b1100001101010000 H
b101001011010011001000 L
b101001011010011001000 >
b101001011010011001000 B
b101001011010011001000 F
b101001011010011001000 O
b101001011010011001000 ,
b101001011010011001000 8
b101001011010011001000 A
1*
#10000
0*
#15000
b101010101000100001000 !
b101010101000100001000 ;
b101010101000100001000 V
b0 ?
b0 K
b0 N
b1100001101010000 <
b1100001101010000 J
b1100001101010000 P
b0 L
b101001011010011001000 =
b101001011010011001000 C
b101001011010011001000 G
b101001011010011001000 M
b101010101000100001000 W
b10 /
1+
1*
#20000
0*
#25000
b101101111100101000011 !
b101101111100101000011 ;
b101101111100101000011 V
b101101111100101000011 W
b1010010110010000011011 M
b101001010111101010011 =
b101001010111101010011 C
b101001010111101010011 G
b0 ?
b0 K
b0 N
b0 L
b101001010111101010011 >
b101001010111101010011 B
b101001010111101010011 F
b101001010111101010011 O
b10101110101 "
b10101110101 0
b10101110101 @
1*
#30000
0*
#35000
b101101111100011010111 !
b101101111100011010111 ;
b101101111100011010111 V
b101001010111011100111 =
b101001010111011100111 C
b101001010111011100111 G
b1111100001001100000010 M
b101101111100011010111 W
b0 ?
b0 K
b0 N
b0 L
b101001010111011100111 >
b101001010111011100111 B
b101001010111011100111 F
b101001010111011100111 O
b10111100001 "
b10111100001 0
b10111100001 @
1*
#40000
0*
#45000
b10100101100000111101001 M
1*
#50000
0*
#55000
b11001110111000011010000 M
1*
#60000
0*
#65000
b11111000001111110110111 M
1*
#70000
0*
#75000
b100100001100111010011110 M
1*
#80000
0*
#85000
b101001010111110110000101 M
1*
#90000
0*
#95000
b101110100010110001101100 M
1*
#100000
0*
#105000
b110011101101101101010011 M
1*
#110000
0*
#115000
b111000111000101000111010 M
1*
#120000
0*
#125000
b111110000011100100100001 M
1*
#130000
0*
#135000
b1000011001110100000001000 M
1*
#140000
0*
#145000
b1001000011001011011101111 M
1*
#150000
0*
#155000
b1001101100100010111010110 M
1*
#160000
0*
#165000
b1010010101111010010111101 M
1*
#170000
0*
#175000
b1010111111010001110100100 M
1*
#180000
0*
#185000
b1011101000101001010001011 M
1*
#190000
0*
#195000
b1100010010000000101110010 M
1*
#200000
0*
#205000
b1100111011011000001011001 M
1*
#210000
0*
#215000
b1101100100101111101000000 M
1*
#220000
0*
#225000
b1110001110000111000100111 M
1*
#230000
0*
#235000
b1110110111011110100001110 M
1*
#240000
0*
#245000
b1111100000110101111110101 M
1*
#250000
0*
#255000
b10000001010001101011011100 M
1*
#260000
0*
#265000
b10000110011100100111000011 M
1*
#270000
0*
#275000
b10001011100111100010101010 M
1*
#280000
0*
#285000
b10010000110010011110010001 M
1*
#290000
0*
#295000
b10010101111101011001111000 M
1*
#300000
0*
#305000
b10011011001000010101011111 M
1*
#310000
0*
#315000
b10100000010011010001000110 M
1*
#320000
0*
#325000
b10100101011110001100101101 M
1*
#330000
0*
#335000
b10101010101001001000010100 M
1*
#340000
0*
#345000
b10101111110100000011111011 M
1*
#350000
0*
#355000
b10110100111110111111100010 M
1*
#360000
0*
#365000
b10111010001001111011001001 M
1*
#370000
0*
#375000
b10111111010100110110110000 M
1*
#380000
0*
#385000
b11000100011111110010010111 M
1*
#390000
0*
#395000
b11001001101010101101111110 M
1*
#400000
0*
#405000
b11001110110101101001100101 M
1*
#410000
0*
#415000
b11010100000000100101001100 M
1*
#420000
0*
#425000
b11011001001011100000110011 M
1*
#430000
0*
#435000
b11011110010110011100011010 M
1*
#440000
0*
#445000
b11100011100001011000000001 M
1*
#450000
0*
#455000
b11101000101100010011101000 M
1*
#460000
0*
#465000
b11101101110111001111001111 M
1*
#470000
0*
#475000
b11110011000010001010110110 M
1*
#480000
0*
#485000
b11111000001101000110011101 M
1*
#490000
0*
#495000
b11111101011000000010000100 M
1*
#500000
0*
#505000
b100000010100010111101101011 M
1*
#510000
0*
#515000
b100000111101101111001010010 M
1*
#520000
0*
#525000
b100001100111000110100111001 M
1*
#530000
0*
#535000
b100010010000011110000100000 M
1*
#540000
0*
#545000
b100010111001110101100000111 M
1*
#550000
0*
#555000
b100011100011001100111101110 M
1*
#560000
0*
#565000
b100100001100100100011010101 M
1*
#570000
0*
#575000
b100100110101111011110111100 M
1*
#580000
0*
#585000
b100101011111010011010100011 M
1*
#590000
0*
#595000
b100110001000101010110001010 M
1*
#600000
0*
#605000
b100110110010000010001110001 M
1*
#610000
0*
#615000
b100111011011011001101011000 M
1*
#620000
0*
#625000
b101000000100110001000111111 M
1*
#630000
0*
#635000
b101000101110001000100100110 M
1*
#640000
0*
#645000
b101001010111100000000001101 M
1*
#650000
0*
#655000
b101010000000110111011110100 M
1*
#660000
0*
#665000
b101010101010001110111011011 M
1*
#670000
0*
#675000
b101011010011100110011000010 M
1*
#680000
0*
#685000
b101011111100111101110101001 M
1*
#690000
0*
#695000
b101100100110010101010010000 M
1*
#700000
0*
#705000
b101101001111101100101110111 M
1*
#710000
0*
#715000
b101101111001000100001011110 M
1*
#720000
0*
#725000
b101110100010011011101000101 M
1*
#730000
0*
#735000
b101111001011110011000101100 M
1*
#740000
0*
#745000
b101111110101001010100010011 M
1*
#750000
0*
#755000
b110000011110100001111111010 M
1*
#760000
0*
#765000
b110001000111111001011100001 M
1*
#770000
0*
#775000
b110001110001010000111001000 M
1*
#780000
0*
#785000
b110010011010101000010101111 M
1*
#790000
0*
#795000
b110011000011111111110010110 M
1*
#800000
0*
#805000
b110011101101010111001111101 M
1*
#810000
0*
#815000
b110100010110101110101100100 M
1*
#820000
0*
#825000
b110101000000000110001001011 M
1*
#830000
0*
#835000
b110101101001011101100110010 M
1*
#840000
0*
#845000
b110110010010110101000011001 M
1*
#850000
0*
#855000
b110110111100001100100000000 M
1*
#860000
0*
#865000
b110111100101100011111100111 M
1*
#870000
0*
#875000
b111000001110111011011001110 M
1*
#880000
0*
#885000
b111000111000010010110110101 M
1*
#890000
0*
#895000
b111001100001101010010011100 M
1*
#900000
0*
#905000
b111010001011000001110000011 M
1*
#910000
0*
#915000
b111010110100011001001101010 M
1*
#920000
0*
#925000
b111011011101110000101010001 M
1*
#930000
0*
#935000
b111100000111001000000111000 M
1*
#940000
0*
#945000
b111100110000011111100011111 M
1*
#950000
0*
#955000
b111101011001110111000000110 M
1*
#960000
0*
#965000
b111110000011001110011101101 M
1*
#970000
0*
#975000
b111110101100100101111010100 M
1*
#980000
0*
#985000
b111111010101111101010111011 M
1*
#990000
0*
#995000
b111111111111010100110100010 M
1*
