Core/SA_rtl/Softmax/softmax.v
`timescale 1ns / 1ps

//find the max value's position
module softmax#(
           parameter BITWIDTH = 8,
           parameter INDEX_WIDTH = 4,
           parameter CLASSES = 10
       )(
           input wire clk,
           input wire rst_n,

           input wire valid,
           output reg ready,

           input signed [BITWIDTH * CLASSES - 1: 0] data_i,
           output reg [INDEX_WIDTH - 1: 0] position_o
       );
localparam IDLE = 2'b01;
localparam BUSY = 2'b10;

//main counter
reg [INDEX_WIDTH - 1: 0] cnt;
reg done;
always @(posedge clk or negedge rst_n) begin
    if (!rst_n) begin
        cnt <= {INDEX_WIDTH{1'b0}};
        done <= 1'b0;
    end
    else begin
        if (cnt >= CLASSES) begin
            cnt <= {INDEX_WIDTH{1'b0}};
            done <= 1'b1;
        end
        else begin
            cnt <= cnt + 'd1;
            done <= 1'b0;
        end
    end
end

//FSM
reg [1: 0] current_state;
reg [1: 0] next_state;

always @(posedge clk or negedge rst_n) begin
    if (!rst_n) begin
        current_state <= IDLE;
    end
    else begin
        current_state <= next_state;
    end
end

always @( * ) begin
    case (current_state)
        IDLE: begin
            if (valid) begin //got posedge of valid signal
                next_state = BUSY;
            end
            else begin
                next_state = IDLE;
            end
        end
        BUSY: begin
            if (done) begin //done after all data were scanned
                next_state = IDLE;
            end
            else begin
                next_state = BUSY;
            end
        end
        default: begin
            next_state = IDLE;
        end
    endcase
end

always @(posedge clk or negedge rst_n) begin
    if (!rst_n) begin
        ready <= 1'b1;
    end
    else begin
        if (current_state == IDLE) begin
            ready <= 1'b1;
        end
        else begin
            ready <= 1'b0;
        end
    end
end

//compare logic
always @(posedge clk or negedge rst_n) begin
    if (!rst_n) begin
        position_o <= {INDEX_WIDTH{1'b0}};
    end
    else begin
        if (data_i[(BITWIDTH * CLASSES - 1) - (cnt * BITWIDTH) -: BITWIDTH] > data_i[(BITWIDTH * CLASSES - 1) - (position_o * BITWIDTH) -: BITWIDTH]) begin
            position_o <= cnt;
        end
        else if(ready) begin
            position_o <= {INDEX_WIDTH{1'b0}};
        end
        else begin
            position_o <= position_o;
        end
    end
end

endmodule

Core/SA_rtl/Softmax/softmax_tb.v
`timescale  1ns / 1ps
`include "softmax.v"

module softmax_tb();
parameter BITWIDTH = 8;
parameter CLASSES = 10;
parameter INDEX_WIDTH = 4;

// softmax Inputs
reg clk = 0;
reg rst_n = 0;
reg valid = 0;
reg [BITWIDTH * CLASSES - 1: 0] data_i = 0;

// softmax Outputs
wire ready;
wire [INDEX_WIDTH - 1: 0] position_o;

initial begin
    forever
        #2 clk = ~clk;
end

initial begin

    data_i = {8'h01, 8'h05, 8'h03, 8'h08, 8'h09, 8'h08, 8'h02, 8'h06, 8'h04, 8'h07};
    data_i = {8'h01, 8'h05, 8'h03, 8'h08, 8'h09, 8'h08, 8'h02, 8'h06, 8'h04, 8'h07};
    #5;

end

integer stage = 0;
always @(posedge clk) begin
    case (stage)
        0: begin
            rst_n = 1'b1;
            stage = 1;
        end
        1: begin
            data_i = {8'h01, 8'h02, 8'h03, 8'h08, 8'h07, 8'h03, 8'h02, 8'h05, 8'h00, 8'h09};
            valid = 1'b1;
            stage = 2;
        end
        2: begin
            stage = 3;
        end
        3: begin
            stage = 4;
        end
        4: begin
            if (ready) begin
                valid = 1'b0;
                data_i = 0;
                $display(position_o);
                stage = 5;
            end
            else begin
                stage = 4;
            end
        end
        5: begin
            stage = 5;
        end
        default: begin
            stage = 5;
        end
    endcase
end

initial begin
    $dumpfile("softmax_tb.vcd");
    $dumpvars();
    #1000;
    $finish;
end

softmax #(
            .BITWIDTH ( BITWIDTH ),
            .CLASSES ( CLASSES ),
            .INDEX_WIDTH ( INDEX_WIDTH )
            )
        u_softmax(
            //ports
            .clk ( clk ),
            .rst_n ( rst_n ),
            .valid ( valid ),
            .ready ( ready ),
            .data_i ( data_i ),
            .position_o ( position_o )
        );


endmodule

Core/SA_rtl/Softmax/softmax_tb.vcd
$date
	Thu Aug 04 11:42:52 2022
$end
$version
	Icarus Verilog
$end
$timescale
	1ps
$end
$scope module softmax_tb $end
$var wire 1 ! ready $end
$var wire 4 " position_o [3:0] $end
$var reg 1 # clk $end
$var reg 80 $ data_i [79:0] $end
$var reg 1 % rst_n $end
$var reg 1 & valid $end
$var integer 32 ' stage [31:0] $end
$scope module u_softmax $end
$var wire 1 # clk $end
$var wire 80 ( data_i [79:0] $end
$var wire 1 % rst_n $end
$var wire 1 & valid $end
$var reg 4 ) cnt [3:0] $end
$var reg 2 * current_state [1:0] $end
$var reg 1 + done $end
$var reg 2 , next_state [1:0] $end
$var reg 4 - position_o [3:0] $end
$var reg 1 ! ready $end
$upscope $end
$upscope $end
$enddefinitions $end
#0
$dumpvars
b0 -
b1 ,
0+
b1 *
b0 )
b1000001010000001100001000000010010000100000000010000001100000010000000111 (
b0 '
0&
0%
b1000001010000001100001000000010010000100000000010000001100000010000000111 $
0#
b0 "
1!
$end
#2000
b1 )
b1 '
1%
1#
#4000
0#
#6000
b10 )
b1 "
b1 -
b10 ,
b10 '
1&
b1000000100000001100001000000001110000001100000010000001010000000000001001 $
b1000000100000001100001000000001110000001100000010000001010000000000001001 (
1#
#8000
0#
#10000
b10 "
b10 -
b10 *
b11 )
b11 '
1#
#12000
0#
#14000
b100 )
0!
b11 "
b11 -
b100 '
1#
#16000
0#
#18000
b101 )
1#
#20000
0#
#22000
b110 )
1#
#24000
0#
#26000
b111 )
1#
#28000
0#
#30000
b1000 )
1#
#32000
0#
#34000
b1001 )
1#
#36000
0#
#38000
b1010 )
b1001 "
b1001 -
1#
#40000
0#
#42000
b1 ,
1+
b0 )
1#
#44000
0#
#46000
b10 ,
0+
b1 )
b1 *
1#
#48000
0#
#50000
1!
b10 *
b10 )
1#
#52000
0#
#54000
b11 )
0!
b0 "
b0 -
b101 '
b0 $
b0 (
0&
1#
#56000
0#
#58000
b100 )
1#
#60000
0#
#62000
b101 )
1#
#64000
0#
#66000
b110 )
1#
#68000
0#
#70000
b111 )
1#
#72000
0#
#74000
b1000 )
1#
#76000
0#
#78000
b1001 )
1#
#80000
0#
#82000
b1010 )
1#
#84000
0#
#86000
b1 ,
1+
b0 )
1#
#88000
0#
#90000
b1 *
0+
b1 )
1#
#92000
0#
#94000
b10 )
1!
1#
#96000
0#
#98000
b11 )
1#
#100000
0#
#102000
b100 )
1#
#104000
0#
#106000
b101 )
1#
#108000
0#
#110000
b110 )
1#
#112000
0#
#114000
b111 )
1#
#116000
0#
#118000
b1000 )
1#
#120000
0#
#122000
b1001 )
1#
#124000
0#
#126000
b1010 )
1#
#128000
0#
#130000
1+
b0 )
1#
#132000
0#
#134000
0+
b1 )
1#
#136000
0#
#138000
b10 )
1#
#140000
0#
#142000
b11 )
1#
#144000
0#
#146000
b100 )
1#
#148000
0#
#150000
b101 )
1#
#152000
0#
#154000
b110 )
1#
#156000
0#
#158000
b111 )
1#
#160000
0#
#162000
b1000 )
1#
#164000
0#
#166000
b1001 )
1#
#168000
0#
#170000
b1010 )
1#
#172000
0#
#174000
1+
b0 )
1#
#176000
0#
#178000
0+
b1 )
1#
#180000
0#
#182000
b10 )
1#
#184000
0#
#186000
b11 )
1#
#188000
0#
#190000
b100 )
1#
#192000
0#
#194000
b101 )
1#
#196000
0#
#198000
b110 )
1#
#200000
0#
#202000
b111 )
1#
#204000
0#
#206000
b1000 )
1#
#208000
0#
#210000
b1001 )
1#
#212000
0#
#214000
b1010 )
1#
#216000
0#
#218000
1+
b0 )
1#
#220000
0#
#222000
0+
b1 )
1#
#224000
0#
#226000
b10 )
1#
#228000
0#
#230000
b11 )
1#
#232000
0#
#234000
b100 )
1#
#236000
0#
#238000
b101 )
1#
#240000
0#
#242000
b110 )
1#
#244000
0#
#246000
b111 )
1#
#248000
0#
#250000
b1000 )
1#
#252000
0#
#254000
b1001 )
1#
#256000
0#
#258000
b1010 )
1#
#260000
0#
#262000
1+
b0 )
1#
#264000
0#
#266000
0+
b1 )
1#
#268000
0#
#270000
b10 )
1#
#272000
0#
#274000
b11 )
1#
#276000
0#
#278000
b100 )
1#
#280000
0#
#282000
b101 )
1#
#284000
0#
#286000
b110 )
1#
#288000
0#
#290000
b111 )
1#
#292000
0#
#294000
b1000 )
1#
#296000
0#
#298000
b1001 )
1#
#300000
0#
#302000
b1010 )
1#
#304000
0#
#306000
1+
b0 )
1#
#308000
0#
#310000
0+
b1 )
1#
#312000
0#
#314000
b10 )
1#
#316000
0#
#318000
b11 )
1#
#320000
0#
#322000
b100 )
1#
#324000
0#
#326000
b101 )
1#
#328000
0#
#330000
b110 )
1#
#332000
0#
#334000
b111 )
1#
#336000
0#
#338000
b1000 )
1#
#340000
0#
#342000
b1001 )
1#
#344000
0#
#346000
b1010 )
1#
#348000
0#
#350000
1+
b0 )
1#
#352000
0#
#354000
0+
b1 )
1#
#356000
0#
#358000
b10 )
1#
#360000
0#
#362000
b11 )
1#
#364000
0#
#366000
b100 )
1#
#368000
0#
#370000
b101 )
1#
#372000
0#
#374000
b110 )
1#
#376000
0#
#378000
b111 )
1#
#380000
0#
#382000
b1000 )
1#
#384000
0#
#386000
b1001 )
1#
#388000
0#
#390000
b1010 )
1#
#392000
0#
#394000
1+
b0 )
1#
#396000
0#
#398000
0+
b1 )
1#
#400000
0#
#402000
b10 )
1#
#404000
0#
#406000
b11 )
1#
#408000
0#
#410000
b100 )
1#
#412000
0#
#414000
b101 )
1#
#416000
0#
#418000
b110 )
1#
#420000
0#
#422000
b111 )
1#
#424000
0#
#426000
b1000 )
1#
#428000
0#
#430000
b1001 )
1#
#432000
0#
#434000
b1010 )
1#
#436000
0#
#438000
1+
b0 )
1#
#440000
0#
#442000
0+
b1 )
1#
#444000
0#
#446000
b10 )
1#
#448000
0#
#450000
b11 )
1#
#452000
0#
#454000
b100 )
1#
#456000
0#
#458000
b101 )
1#
#460000
0#
#462000
b110 )
1#
#464000
0#
#466000
b111 )
1#
#468000
0#
#470000
b1000 )
1#
#472000
0#
#474000
b1001 )
1#
#476000
0#
#478000
b1010 )
1#
#480000
0#
#482000
1+
b0 )
1#
#484000
0#
#486000
0+
b1 )
1#
#488000
0#
#490000
b10 )
1#
#492000
0#
#494000
b11 )
1#
#496000
0#
#498000
b100 )
1#
#500000
0#
#502000
b101 )
1#
#504000
0#
#506000
b110 )
1#
#508000
0#
#510000
b111 )
1#
#512000
0#
#514000
b1000 )
1#
#516000
0#
#518000
b1001 )
1#
#520000
0#
#522000
b1010 )
1#
#524000
0#
#526000
1+
b0 )
1#
#528000
0#
#530000
0+
b1 )
1#
#532000
0#
#534000
b10 )
1#
#536000
0#
#538000
b11 )
1#
#540000
0#
#542000
b100 )
1#
#544000
0#
#546000
b101 )
1#
#548000
0#
#550000
b110 )
1#
#552000
0#
#554000
b111 )
1#
#556000
0#
#558000
b1000 )
1#
#560000
0#
#562000
b1001 )
1#
#564000
0#
#566000
b1010 )
1#
#568000
0#
#570000
1+
b0 )
1#
#572000
0#
#574000
0+
b1 )
1#
#576000
0#
#578000
b10 )
1#
#580000
0#
#582000
b11 )
1#
#584000
0#
#586000
b100 )
1#
#588000
0#
#590000
b101 )
1#
#592000
0#
#594000
b110 )
1#
#596000
0#
#598000
b111 )
1#
#600000
0#
#602000
b1000 )
1#
#604000
0#
#606000
b1001 )
1#
#608000
0#
#610000
b1010 )
1#
#612000
0#
#614000
1+
b0 )
1#
#616000
0#
#618000
0+
b1 )
1#
#620000
0#
#622000
b10 )
1#
#624000
0#
#626000
b11 )
1#
#628000
0#
#630000
b100 )
1#
#632000
0#
#634000
b101 )
1#
#636000
0#
#638000
b110 )
1#
#640000
0#
#642000
b111 )
1#
#644000
0#
#646000
b1000 )
1#
#648000
0#
#650000
b1001 )
1#
#652000
0#
#654000
b1010 )
1#
#656000
0#
#658000
1+
b0 )
1#
#660000
0#
#662000
0+
b1 )
1#
#664000
0#
#666000
b10 )
1#
#668000
0#
#670000
b11 )
1#
#672000
0#
#674000
b100 )
1#
#676000
0#
#678000
b101 )
1#
#680000
0#
#682000
b110 )
1#
#684000
0#
#686000
b111 )
1#
#688000
0#
#690000
b1000 )
1#
#692000
0#
#694000
b1001 )
1#
#696000
0#
#698000
b1010 )
1#
#700000
0#
#702000
1+
b0 )
1#
#704000
0#
#706000
0+
b1 )
1#
#708000
0#
#710000
b10 )
1#
#712000
0#
#714000
b11 )
1#
#716000
0#
#718000
b100 )
1#
#720000
0#
#722000
b101 )
1#
#724000
0#
#726000
b110 )
1#
#728000
0#
#730000
b111 )
1#
#732000
0#
#734000
b1000 )
1#
#736000
0#
#738000
b1001 )
1#
#740000
0#
#742000
b1010 )
1#
#744000
0#
#746000
1+
b0 )
1#
#748000
0#
#750000
0+
b1 )
1#
#752000
0#
#754000
b10 )
1#
#756000
0#
#758000
b11 )
1#
#760000
0#
#762000
b100 )
1#
#764000
0#
#766000
b101 )
1#
#768000
0#
#770000
b110 )
1#
#772000
0#
#774000
b111 )
1#
#776000
0#
#778000
b1000 )
1#
#780000
0#
#782000
b1001 )
1#
#784000
0#
#786000
b1010 )
1#
#788000
0#
#790000
1+
b0 )
1#
#792000
0#
#794000
0+
b1 )
1#
#796000
0#
#798000
b10 )
1#
#800000
0#
#802000
b11 )
1#
#804000
0#
#806000
b100 )
1#
#808000
0#
#810000
b101 )
1#
#812000
0#
#814000
b110 )
1#
#816000
0#
#818000
b111 )
1#
#820000
0#
#822000
b1000 )
1#
#824000
0#
#826000
b1001 )
1#
#828000
0#
#830000
b1010 )
1#
#832000
0#
#834000
1+
b0 )
1#
#836000
0#
#838000
0+
b1 )
1#
#840000
0#
#842000
b10 )
1#
#844000
0#
#846000
b11 )
1#
#848000
0#
#850000
b100 )
1#
#852000
0#
#854000
b101 )
1#
#856000
0#
#858000
b110 )
1#
#860000
0#
#862000
b111 )
1#
#864000
0#
#866000
b1000 )
1#
#868000
0#
#870000
b1001 )
1#
#872000
0#
#874000
b1010 )
1#
#876000
0#
#878000
1+
b0 )
1#
#880000
0#
#882000
0+
b1 )
1#
#884000
0#
#886000
b10 )
1#
#888000
0#
#890000
b11 )
1#
#892000
0#
#894000
b100 )
1#
#896000
0#
#898000
b101 )
1#
#900000
0#
#902000
b110 )
1#
#904000
0#
#906000
b111 )
1#
#908000
0#
#910000
b1000 )
1#
#912000
0#
#914000
b1001 )
1#
#916000
0#
#918000
b1010 )
1#
#920000
0#
#922000
1+
b0 )
1#
#924000
0#
#926000
0+
b1 )
1#
#928000
0#
#930000
b10 )
1#
#932000
0#
#934000
b11 )
1#
#936000
0#
#938000
b100 )
1#
#940000
0#
#942000
b101 )
1#
#944000
0#
#946000
b110 )
1#
#948000
0#
#950000
b111 )
1#
#952000
0#
#954000
b1000 )
1#
#956000
0#
#958000
b1001 )
1#
#960000
0#
#962000
b1010 )
1#
#964000
0#
#966000
1+
b0 )
1#
#968000
0#
#970000
0+
b1 )
1#
#972000
0#
#974000
b10 )
1#
#976000
0#
#978000
b11 )
1#
#980000
0#
#982000
b100 )
1#
#984000
0#
#986000
b101 )
1#
#988000
0#
#990000
b110 )
1#
#992000
0#
#994000
b111 )
1#
#996000
0#
#998000
b1000 )
1#
